unzip_http.py
unzip_http-0.6.data/scripts/unzip-http
unzip_http-0.6.data/scripts/unzip_http.py
unzip_http-0.6.dist-info/LICENSE-mit.txt
unzip_http-0.6.dist-info/METADATA
unzip_http-0.6.dist-info/WHEEL
unzip_http-0.6.dist-info/entry_points.txt
unzip_http-0.6.dist-info/top_level.txt
unzip_http-0.6.dist-info/RECORD
