Metadata-Version: 2.1
Name: unzip-http
Version: 0.6
Summary: extract files from .zip files over http without downloading entire archive
Home-page: https://github.com/saulpw/unzip-http
Author: Saul Pwanson
Keywords: http zip unzip
Classifier: Development Status :: 4 - Beta
Classifier: Programming Language :: Python :: 3
Requires-Python: >=3.8
License-File: LICENSE-mit.txt
Requires-Dist: urllib3
